{
  "project_info": {
    "project_number": "707694584657",
    "project_id": "boualot-book-4a2ab",
    "storage_bucket": "boualot-book-4a2ab.firebasestorage.app"
  },
  "client": [
    {
      "client_info": {
        "mobilesdk_app_id": "1:707694584657:android:2e92c62098278ec8e9a970",
        "android_client_info": {
          "package_name": "com.boualot.book"
        }
      },
      "oauth_client": [],
      "api_key": [
        {
          "current_key": "AIzaSyBiAouRvjxINJsEUXPHXJkVw5pSpGluRDc"
        }
      ],
      "services": {
        "appinvite_service": {
          "other_platform_oauth_client": []
        }
      }
    }
  ],
  "configuration_version": "1"
}